FastDataTime/Dtime.py
FastDataTime/OStime.py
FastDataTime/__init__.py
FastDataTime/programtime.py
FastDataTime-0.0.8.dist-info/LICENSE.txt
FastDataTime-0.0.8.dist-info/METADATA
FastDataTime-0.0.8.dist-info/WHEEL
FastDataTime-0.0.8.dist-info/top_level.txt
FastDataTime-0.0.8.dist-info/RECORD
