Metadata-Version: 2.1
Name: FastDataTime
Version: 0.0.8
Summary: 一个基于其他模块，快速执行时间处理的模块|A module that performs time processing quickly based on other modules
Home-page: https://codechina.csdn.net/qq_53280175/fastdatatime
Author: PYmili
Author-email: mc2005wj@163.com
Maintainer: PYmili
Maintainer-email: mc2005wj@163.com
License: MIT License
Platform: UNKNOWN
Classifier: Intended Audience :: Developers
Classifier: Operating System :: OS Independent
Classifier: Natural Language :: Chinese (Simplified)
Classifier: Natural Language :: English
Classifier: License :: OSI Approved :: MIT License
Classifier: Programming Language :: Python :: 3.6
Classifier: Programming Language :: Python :: 3.7
Classifier: Programming Language :: Python :: 3.8
Classifier: Programming Language :: Python :: 3.9
Classifier: Topic :: Software Development :: Libraries
Requires-Python: >=3.7
License-File: LICENSE.txt
Requires-Dist: schedule (>=1.1.0)
Requires-Dist: pytz (>=2021.1)
Requires-Dist: timezones (>=2.0.9)
